trainers_cooks/__init__.py
trainers_cooks-0.0.2.dist-info/METADATA
trainers_cooks-0.0.2.dist-info/WHEEL
trainers_cooks-0.0.2.dist-info/top_level.txt
trainers_cooks-0.0.2.dist-info/RECORD
